payplug_dj/models.py
payplug_dj/views.py
payplug_dj/signals.py
payplug_dj/admin.py
payplug_dj/forms.py
payplug_dj/urls.py
payplug_dj/__init__.py
payplug_dj/templates/payplug_dj/base.html
payplug_dj/templates/payplug_dj/payment_return.html
payplug_dj/templates/payplug_dj/payment_cancel.html
payplug_dj/templates/payplug_dj/payment_notification.html
payplug_dj/management/commands/check_payment.py
payplug_dj/migrations/0001_initial.py
payplug_dj/migrations/__init__.py
payplug_dj-0.1.0.dist-info/WHEEL
payplug_dj-0.1.0.dist-info/top_level.txt
payplug_dj-0.1.0.dist-info/DESCRIPTION.rst
payplug_dj-0.1.0.dist-info/metadata.json
payplug_dj-0.1.0.dist-info/METADATA
payplug_dj-0.1.0.dist-info/RECORD
