Metadata-Version: 2.0
Name: payplug-dj
Version: 0.1.0
Summary: A Django module for using https://www.payplug.com payment solution.
Home-page: https://github.com/alexandrenorman/payplug_dj
Author: Alexandre Norman
Author-email: norman@xael.org
License: BSD
Keywords: payplug_dj
Platform: UNKNOWN
Classifier: Development Status :: 3 - Alpha
Classifier: Framework :: Django
Classifier: Framework :: Django :: 1.8
Classifier: Framework :: Django :: 1.9
Classifier: Intended Audience :: Developers
Classifier: License :: OSI Approved :: BSD License
Classifier: Natural Language :: English
Classifier: Programming Language :: Python :: 2
Classifier: Programming Language :: Python :: 2.7
Classifier: Programming Language :: Python :: 3
Classifier: Programming Language :: Python :: 3.3
Classifier: Programming Language :: Python :: 3.4
Classifier: Programming Language :: Python :: 3.5
